[
  {
    "label": "Ackley_10d",
    "name": "Ackley",
    "dim": "10",
    "maximize": "False",
    "repetitions": "20",
    "iter_max": "300",
    "n_starts": "10",
    "seed": "20260828",
    "evolution_strategy": "sobol",
    "best_opt": "0.03153000336684686",
    "algo": "SMCO",
    "time_avg": "0.9267632810049691",
    "rMSE": "0.20616559505386522",
    "AE50": "0.1930029793560184",
    "AE95": "0.25933842710544897",
    "AE99": "0.26371417808612735",
    "fopt_mean": "0.23369173527927717",
    "fopt_sd": "0.041484134368403834"
  },
  {
    "label": "Ackley_10d",
    "name": "Ackley",
    "dim": "10",
    "maximize": "False",
    "repetitions": "20",
    "iter_max": "300",
    "n_starts": "10",
    "seed": "20260828",
    "evolution_strategy": "sobol",
    "best_opt": "0.03153000336684686",
    "algo": "SMCO_BR",
    "time_avg": "0.9529520799493184",
    "rMSE": "0.02694338815952947",
    "AE50": "0.027669215302811523",
    "AE95": "0.03539745390470746",
    "AE99": "0.035756985339105575",
    "fopt_mean": "0.05730520075258196",
    "fopt_sd": "0.008051502981069804"
  },
  {
    "label": "Ackley_10d",
    "name": "Ackley",
    "dim": "10",
    "maximize": "False",
    "repetitions": "20",
    "iter_max": "300",
    "n_starts": "10",
    "seed": "20260828",
    "evolution_strategy": "sobol",
    "best_opt": "0.03153000336684686",
    "algo": "SMCO_BR_EVO",
    "time_avg": "0.9476631295488914",
    "rMSE": "0.02993847045214669",
    "AE50": "0.029646104946028373",
    "AE95": "0.038203903646855684",
    "AE99": "0.03887282835067285",
    "fopt_mean": "0.060768130129287015",
    "fopt_sd": "0.006604938856846065"
  },
  {
    "label": "Ackley_10d",
    "name": "Ackley",
    "dim": "10",
    "maximize": "False",
    "repetitions": "20",
    "iter_max": "300",
    "n_starts": "10",
    "seed": "20260828",
    "evolution_strategy": "sobol",
    "best_opt": "0.03153000336684686",
    "algo": "SMCO_EVO",
    "time_avg": "0.9345802713563899",
    "rMSE": "0.22733682060994329",
    "AE50": "0.2276116672785502",
    "AE95": "0.2619188777665773",
    "AE99": "0.2650566143143724",
    "fopt_mean": "0.2575854255294173",
    "fopt_sd": "0.024729613952752284"
  },
  {
    "label": "Ackley_10d",
    "name": "Ackley",
    "dim": "10",
    "maximize": "False",
    "repetitions": "20",
    "iter_max": "300",
    "n_starts": "10",
    "seed": "20260828",
    "evolution_strategy": "sobol",
    "best_opt": "0.03153000336684686",
    "algo": "SMCO_R",
    "time_avg": "0.9342102134047309",
    "rMSE": "0.02205152661062768",
    "AE50": "0.021354880783476915",
    "AE95": "0.029506092517503826",
    "AE99": "0.030806930429749604",
    "fopt_mean": "0.051999511298558065",
    "fopt_sd": "0.008414840955611994"
  },
  {
    "label": "Ackley_10d",
    "name": "Ackley",
    "dim": "10",
    "maximize": "False",
    "repetitions": "20",
    "iter_max": "300",
    "n_starts": "10",
    "seed": "20260828",
    "evolution_strategy": "sobol",
    "best_opt": "0.03153000336684686",
    "algo": "SMCO_R_EVO",
    "time_avg": "0.9285168057482224",
    "rMSE": "0.02492611940859723",
    "AE50": "0.022898707487664538",
    "AE95": "0.03717110381007558",
    "AE99": "0.03959315932332742",
    "fopt_mean": "0.0544153033292674",
    "fopt_sd": "0.0101345928904126"
  },
  {
    "label": "Bukin6_2d",
    "name": "Bukin6",
    "dim": "2",
    "maximize": "False",
    "repetitions": "20",
    "iter_max": "300",
    "n_starts": "10",
    "seed": "20262028",
    "evolution_strategy": "sobol",
    "best_opt": "0.02853249840800938",
    "algo": "SMCO",
    "time_avg": "0.07969647409918253",
    "rMSE": "0.15798384501046223",
    "AE50": "0.1385584660120707",
    "AE95": "0.28139339680661896",
    "AE99": "0.33404599232891585",
    "fopt_mean": "0.1649648297902512",
    "fopt_sd": "0.08172556282362199"
  },
  {
    "label": "Bukin6_2d",
    "name": "Bukin6",
    "dim": "2",
    "maximize": "False",
    "repetitions": "20",
    "iter_max": "300",
    "n_starts": "10",
    "seed": "20262028",
    "evolution_strategy": "sobol",
    "best_opt": "0.02853249840800938",
    "algo": "SMCO_BR",
    "time_avg": "0.08488230460789055",
    "rMSE": "0.11753933043870181",
    "AE50": "0.11074545337061752",
    "AE95": "0.17327865598266767",
    "AE99": "0.1870161909249252",
    "fopt_mean": "0.13756744060957377",
    "fopt_sd": "0.04503654164389113"
  },
  {
    "label": "Bukin6_2d",
    "name": "Bukin6",
    "dim": "2",
    "maximize": "False",
    "repetitions": "20",
    "iter_max": "300",
    "n_starts": "10",
    "seed": "20262028",
    "evolution_strategy": "sobol",
    "best_opt": "0.02853249840800938",
    "algo": "SMCO_BR_EVO",
    "time_avg": "0.08436739555036184",
    "rMSE": "0.10929831020281568",
    "AE50": "0.10982397487212246",
    "AE95": "0.14983945641793156",
    "AE99": "0.1670576537169253",
    "fopt_mean": "0.12778472047086226",
    "fopt_sd": "0.0469615411382667"
  },
  {
    "label": "Bukin6_2d",
    "name": "Bukin6",
    "dim": "2",
    "maximize": "False",
    "repetitions": "20",
    "iter_max": "300",
    "n_starts": "10",
    "seed": "20262028",
    "evolution_strategy": "sobol",
    "best_opt": "0.02853249840800938",
    "algo": "SMCO_EVO",
    "time_avg": "0.08831604079459794",
    "rMSE": "0.20495215936763586",
    "AE50": "0.16767465579775828",
    "AE95": "0.333776295029666",
    "AE99": "0.37359700141242597",
    "fopt_mean": "0.213910798737554",
    "fopt_sd": "0.08967939032368204"
  },
  {
    "label": "Bukin6_2d",
    "name": "Bukin6",
    "dim": "2",
    "maximize": "False",
    "repetitions": "20",
    "iter_max": "300",
    "n_starts": "10",
    "seed": "20262028",
    "evolution_strategy": "sobol",
    "best_opt": "0.02853249840800938",
    "algo": "SMCO_R",
    "time_avg": "0.08166215980018024",
    "rMSE": "0.0971485959035733",
    "AE50": "0.08869798844692643",
    "AE95": "0.1372505111466445",
    "AE99": "0.14486683706822046",
    "fopt_mean": "0.12025598119284879",
    "fopt_sd": "0.03284176403773969"
  },
  {
    "label": "Bukin6_2d",
    "name": "Bukin6",
    "dim": "2",
    "maximize": "False",
    "repetitions": "20",
    "iter_max": "300",
    "n_starts": "10",
    "seed": "20262028",
    "evolution_strategy": "sobol",
    "best_opt": "0.02853249840800938",
    "algo": "SMCO_R_EVO",
    "time_avg": "0.08553788474819157",
    "rMSE": "0.11428633159625307",
    "AE50": "0.08819758610001102",
    "AE95": "0.16101765984032773",
    "AE99": "0.23584152589481824",
    "fopt_mean": "0.13256161610503953",
    "fopt_sd": "0.04855066004111109"
  },
  {
    "label": "DixonPrice_10d",
    "name": "DixonPrice",
    "dim": 10,
    "maximize": false,
    "repetitions": 20,
    "iter_max": 300,
    "n_starts": 10,
    "seed": 20261128,
    "evolution_strategy": "sobol",
    "best_opt": 0.0033657749430421554,
    "algo": "SMCO",
    "time_avg": 0.7626386388525134,
    "rMSE": 0.6678273906450657,
    "AE50": 0.6677407191893052,
    "AE95": 0.6696594902250879,
    "AE99": 0.6710203240496281,
    "fopt_mean": 0.6711919655980825,
    "fopt_sd": 0.0012988946615969939
  },
  {
    "label": "DixonPrice_10d",
    "name": "DixonPrice",
    "dim": 10,
    "maximize": false,
    "repetitions": 20,
    "iter_max": 300,
    "n_starts": 10,
    "seed": 20261128,
    "evolution_strategy": "sobol",
    "best_opt": 0.0033657749430421554,
    "algo": "SMCO_BR",
    "time_avg": 0.7244896892516408,
    "rMSE": 0.3798314242411516,
    "AE50": 0.012734670800040697,
    "AE95": 0.6638189792405716,
    "AE99": 0.6638469485168315,
    "fopt_mean": 0.23596282726881235,
    "fopt_sd": 0.3080849542618922
  },
  {
    "label": "DixonPrice_10d",
    "name": "DixonPrice",
    "dim": 10,
    "maximize": false,
    "repetitions": 20,
    "iter_max": 300,
    "n_starts": 10,
    "seed": 20261128,
    "evolution_strategy": "sobol",
    "best_opt": 0.0033657749430421554,
    "algo": "SMCO_BR_EVO",
    "time_avg": 0.7659774384927005,
    "rMSE": 0.39149999817547537,
    "AE50": 0.008727082048024448,
    "AE95": 0.6638365449838982,
    "AE99": 0.6638472139886932,
    "fopt_mean": 0.2396574306335056,
    "fopt_sd": 0.3202605880125822
  },
  {
    "label": "DixonPrice_10d",
    "name": "DixonPrice",
    "dim": 10,
    "maximize": false,
    "repetitions": 20,
    "iter_max": 300,
    "n_starts": 10,
    "seed": 20261128,
    "evolution_strategy": "sobol",
    "best_opt": 0.0033657749430421554,
    "algo": "SMCO_EVO",
    "time_avg": 0.8059345999587094,
    "rMSE": 0.6681368906336319,
    "AE50": 0.6680587768707738,
    "AE95": 0.6698653373447293,
    "AE99": 0.6708492264859715,
    "fopt_mean": 0.6715015054439595,
    "fopt_sd": 0.0012774372301854007
  },
  {
    "label": "DixonPrice_10d",
    "name": "DixonPrice",
    "dim": 10,
    "maximize": false,
    "repetitions": 20,
    "iter_max": 300,
    "n_starts": 10,
    "seed": 20261128,
    "evolution_strategy": "sobol",
    "best_opt": 0.0033657749430421554,
    "algo": "SMCO_R",
    "time_avg": 0.7354860737512354,
    "rMSE": 0.6637653803981874,
    "AE50": 0.6637640461923036,
    "AE95": 0.664048728978814,
    "AE99": 0.6640914519553293,
    "fopt_mean": 0.6671311364699735,
    "fopt_sd": 0.00016239060337803885
  },
  {
    "label": "DixonPrice_10d",
    "name": "DixonPrice",
    "dim": 10,
    "maximize": false,
    "repetitions": 20,
    "iter_max": 300,
    "n_starts": 10,
    "seed": 20261128,
    "evolution_strategy": "sobol",
    "best_opt": 0.0033657749430421554,
    "algo": "SMCO_R_EVO",
    "time_avg": 0.7534123014047509,
    "rMSE": 0.6469436694562056,
    "AE50": 0.6637433291923243,
    "AE95": 0.663927837566026,
    "AE99": 0.6639913458761423,
    "fopt_mean": 0.6340408152398199,
    "fopt_sd": 0.1479157121155509
  },
  {
    "label": "DropWave_2d",
    "name": "DropWave",
    "dim": "2",
    "maximize": "False",
    "repetitions": "20",
    "iter_max": "300",
    "n_starts": "10",
    "seed": "20261528",
    "evolution_strategy": "sobol",
    "best_opt": "-0.99999325172885",
    "algo": "SMCO",
    "time_avg": "0.13784092254936695",
    "rMSE": "0.05069702957098222",
    "AE50": "0.06000755489512738",
    "AE95": "0.0637479268678002",
    "AE99": "0.06374792842322735",
    "fopt_mean": "-0.9550044180481476",
    "fopt_sd": "0.023977920795053002"
  },
  {
    "label": "DropWave_2d",
    "name": "DropWave",
    "dim": "2",
    "maximize": "False",
    "repetitions": "20",
    "iter_max": "300",
    "n_starts": "10",
    "seed": "20261528",
    "evolution_strategy": "sobol",
    "best_opt": "-0.99999325172885",
    "algo": "SMCO_BR",
    "time_avg": "0.1450753468554467",
    "rMSE": "0.04727688152025257",
    "AE50": "0.06374792392929163",
    "AE95": "0.06374792456870172",
    "AE99": "0.0637479246956201",
    "fopt_mean": "-0.9648729692954369",
    "fopt_sd": "0.032471352363150525"
  },
  {
    "label": "DropWave_2d",
    "name": "DropWave",
    "dim": "2",
    "maximize": "False",
    "repetitions": "20",
    "iter_max": "300",
    "n_starts": "10",
    "seed": "20261528",
    "evolution_strategy": "sobol",
    "best_opt": "-0.99999325172885",
    "algo": "SMCO_BR_EVO",
    "time_avg": "0.14553006090864073",
    "rMSE": "0.04937919217137199",
    "AE50": "0.06374792395597623",
    "AE95": "0.06374792588823651",
    "AE99": "0.06374792741099551",
    "fopt_mean": "-0.9616597583470992",
    "fopt_sd": "0.031934932278463536"
  },
  {
    "label": "DropWave_2d",
    "name": "DropWave",
    "dim": "2",
    "maximize": "False",
    "repetitions": "20",
    "iter_max": "300",
    "n_starts": "10",
    "seed": "20261528",
    "evolution_strategy": "sobol",
    "best_opt": "-0.99999325172885",
    "algo": "SMCO_EVO",
    "time_avg": "0.14678935724950862",
    "rMSE": "0.057523491755924076",
    "AE50": "0.06374792404759355",
    "AE95": "0.06374793095916047",
    "AE99": "0.06374793733204238",
    "fopt_mean": "-0.9450418904537768",
    "fopt_sd": "0.0174506823214581"
  },
  {
    "label": "DropWave_2d",
    "name": "DropWave",
    "dim": "2",
    "maximize": "False",
    "repetitions": "20",
    "iter_max": "300",
    "n_starts": "10",
    "seed": "20261528",
    "evolution_strategy": "sobol",
    "best_opt": "-0.99999325172885",
    "algo": "SMCO_R",
    "time_avg": "0.14015052880567963",
    "rMSE": "0.0427638840310589",
    "AE50": "0.0004259515455318219",
    "AE95": "0.0637479245359731",
    "AE99": "0.0637479268546818",
    "fopt_mean": "-0.971172125429443",
    "fopt_sd": "0.032413325009379525"
  },
  {
    "label": "DropWave_2d",
    "name": "DropWave",
    "dim": "2",
    "maximize": "False",
    "repetitions": "20",
    "iter_max": "300",
    "n_starts": "10",
    "seed": "20261528",
    "evolution_strategy": "sobol",
    "best_opt": "-0.99999325172885",
    "algo": "SMCO_R_EVO",
    "time_avg": "0.1415880499931518",
    "rMSE": "0.05139541068558369",
    "AE50": "0.06374792393479128",
    "AE95": "0.06374792405789409",
    "AE99": "0.06374792418539432",
    "fopt_mean": "-0.9584926660613959",
    "fopt_sd": "0.0311057555817862"
  },
  {
    "label": "Easom_2d",
    "name": "Easom",
    "dim": "2",
    "maximize": "False",
    "repetitions": "20",
    "iter_max": "300",
    "n_starts": "10",
    "seed": "20262128",
    "evolution_strategy": "sobol",
    "best_opt": "-0.9999987397728141",
    "algo": "SMCO",
    "time_avg": "0.054134258101112206",
    "rMSE": "0.7107570450447097",
    "AE50": "0.6275647704531944",
    "AE95": "0.9999987397728141",
    "AE99": "0.9999987397728141",
    "fopt_mean": "-0.39513970380707053",
    "fopt_sd": "0.38295406305701024"
  },
  {
    "label": "Easom_2d",
    "name": "Easom",
    "dim": "2",
    "maximize": "False",
    "repetitions": "20",
    "iter_max": "300",
    "n_starts": "10",
    "seed": "20262128",
    "evolution_strategy": "sobol",
    "best_opt": "-0.9999987397728141",
    "algo": "SMCO_BR",
    "time_avg": "0.060853003794909453",
    "rMSE": "0.6708177139630339",
    "AE50": "0.005307350291232693",
    "AE95": "0.9999987397728141",
    "AE99": "0.9999987397728141",
    "fopt_mean": "-0.5485660844785529",
    "fopt_sd": "0.5090806606552885"
  },
  {
    "label": "Easom_2d",
    "name": "Easom",
    "dim": "2",
    "maximize": "False",
    "repetitions": "20",
    "iter_max": "300",
    "n_starts": "10",
    "seed": "20262128",
    "evolution_strategy": "sobol",
    "best_opt": "-0.9999987397728141",
    "algo": "SMCO_BR_EVO",
    "time_avg": "0.06125488135439809",
    "rMSE": "0.6324447899002763",
    "AE50": "0.003018380843314461",
    "AE95": "0.9999987397728141",
    "AE99": "0.9999987397728141",
    "fopt_mean": "-0.5990029931869504",
    "fopt_sd": "0.501774559876246"
  },
  {
    "label": "Easom_2d",
    "name": "Easom",
    "dim": "2",
    "maximize": "False",
    "repetitions": "20",
    "iter_max": "300",
    "n_starts": "10",
    "seed": "20262128",
    "evolution_strategy": "sobol",
    "best_opt": "-0.9999987397728141",
    "algo": "SMCO_EVO",
    "time_avg": "0.057169167246320284",
    "rMSE": "0.7633387169951487",
    "AE50": "0.8806410669788846",
    "AE95": "0.9999987397728141",
    "AE99": "0.9999987397728141",
    "fopt_mean": "-0.34376441356651843",
    "fopt_sd": "0.40005592500150455"
  },
  {
    "label": "Easom_2d",
    "name": "Easom",
    "dim": "2",
    "maximize": "False",
    "repetitions": "20",
    "iter_max": "300",
    "n_starts": "10",
    "seed": "20262128",
    "evolution_strategy": "sobol",
    "best_opt": "-0.9999987397728141",
    "algo": "SMCO_R",
    "time_avg": "0.059211468943976796",
    "rMSE": "0.4999952874246112",
    "AE50": "0.0016490116502008156",
    "AE95": "0.9999987397728141",
    "AE99": "0.9999987397728141",
    "fopt_mean": "-0.7488448597485103",
    "fopt_sd": "0.44357046078332796"
  },
  {
    "label": "Easom_2d",
    "name": "Easom",
    "dim": "2",
    "maximize": "False",
    "repetitions": "20",
    "iter_max": "300",
    "n_starts": "10",
    "seed": "20262128",
    "evolution_strategy": "sobol",
    "best_opt": "-0.9999987397728141",
    "algo": "SMCO_R_EVO",
    "time_avg": "0.05955128165660426",
    "rMSE": "0.5477084794180617",
    "AE50": "0.00149518421204059",
    "AE95": "0.9999987397728141",
    "AE99": "0.9999987397728141",
    "fopt_mean": "-0.6992604878706338",
    "fopt_sd": "0.4696483368260107"
  },
  {
    "label": "Eggholder_2d",
    "name": "Eggholder",
    "dim": "2",
    "maximize": "False",
    "repetitions": "20",
    "iter_max": "300",
    "n_starts": "10",
    "seed": "20261928",
    "evolution_strategy": "sobol",
    "best_opt": "-959.6406408392686",
    "algo": "SMCO",
    "time_avg": "0.10607950160338078",
    "rMSE": "170.70248772548396",
    "AE50": "68.29374992025265",
    "AE95": "335.09721943765544",
    "AE99": "387.9191430621163",
    "fopt_mean": "-830.4683645164343",
    "fopt_sd": "114.49597715408963"
  },
  {
    "label": "Eggholder_2d",
    "name": "Eggholder",
    "dim": "2",
    "maximize": "False",
    "repetitions": "20",
    "iter_max": "300",
    "n_starts": "10",
    "seed": "20261928",
    "evolution_strategy": "sobol",
    "best_opt": "-959.6406408392686",
    "algo": "SMCO_BR",
    "time_avg": "0.1104037395096384",
    "rMSE": "162.5013784892316",
    "AE50": "68.55435345851316",
    "AE95": "333.1961716554627",
    "AE99": "381.5535838458663",
    "fopt_mean": "-838.4643841576647",
    "fopt_sd": "111.0856133919596"
  },
  {
    "label": "Eggholder_2d",
    "name": "Eggholder",
    "dim": "2",
    "maximize": "False",
    "repetitions": "20",
    "iter_max": "300",
    "n_starts": "10",
    "seed": "20261928",
    "evolution_strategy": "sobol",
    "best_opt": "-959.6406408392686",
    "algo": "SMCO_BR_EVO",
    "time_avg": "0.11336724589345977",
    "rMSE": "127.8160548216109",
    "AE50": "65.06646843711212",
    "AE95": "216.637480009025",
    "AE99": "358.2418914356588",
    "fopt_mean": "-867.6362080673758",
    "fopt_sd": "91.02994429528945"
  },
  {
    "label": "Eggholder_2d",
    "name": "Eggholder",
    "dim": "2",
    "maximize": "False",
    "repetitions": "20",
    "iter_max": "300",
    "n_starts": "10",
    "seed": "20261928",
    "evolution_strategy": "sobol",
    "best_opt": "-959.6406408392686",
    "algo": "SMCO_EVO",
    "time_avg": "0.10634106480283663",
    "rMSE": "117.53879046187981",
    "AE50": "65.1288287611302",
    "AE95": "228.2723528322162",
    "AE99": "230.17347335775028",
    "fopt_mean": "-868.1265782307333",
    "fopt_sd": "75.67620503533658"
  },
  {
    "label": "Eggholder_2d",
    "name": "Eggholder",
    "dim": "2",
    "maximize": "False",
    "repetitions": "20",
    "iter_max": "300",
    "n_starts": "10",
    "seed": "20261928",
    "evolution_strategy": "sobol",
    "best_opt": "-959.6406408392686",
    "algo": "SMCO_R",
    "time_avg": "0.10343507224170026",
    "rMSE": "165.06749250150708",
    "AE50": "67.91096522849477",
    "AE95": "332.6380901613022",
    "AE99": "372.37482841231156",
    "fopt_mean": "-837.640808130615",
    "fopt_sd": "114.07900263365791"
  },
  {
    "label": "Eggholder_2d",
    "name": "Eggholder",
    "dim": "2",
    "maximize": "False",
    "repetitions": "20",
    "iter_max": "300",
    "n_starts": "10",
    "seed": "20261928",
    "evolution_strategy": "sobol",
    "best_opt": "-959.6406408392686",
    "algo": "SMCO_R_EVO",
    "time_avg": "0.10827257685887162",
    "rMSE": "131.9039405229628",
    "AE50": "65.06504268724973",
    "AE95": "242.96967517876797",
    "AE99": "242.96972596355155",
    "fopt_mean": "-864.2582902254559",
    "fopt_sd": "93.47590016947517"
  },
  {
    "label": "Griewank_10d",
    "name": "Griewank",
    "dim": "10",
    "maximize": "False",
    "repetitions": "20",
    "iter_max": "300",
    "n_starts": "10",
    "seed": "20260928",
    "evolution_strategy": "sobol",
    "best_opt": "0.029172056948342462",
    "algo": "SMCO",
    "time_avg": "0.625842704801471",
    "rMSE": "0.3092422655766645",
    "AE50": "0.28395061738763483",
    "AE95": "0.4186303385572558",
    "AE99": "0.44531695632748797",
    "fopt_mean": "0.3280130438761145",
    "fopt_sd": "0.08159491309623756"
  },
  {
    "label": "Griewank_10d",
    "name": "Griewank",
    "dim": "10",
    "maximize": "False",
    "repetitions": "20",
    "iter_max": "300",
    "n_starts": "10",
    "seed": "20260928",
    "evolution_strategy": "sobol",
    "best_opt": "0.029172056948342462",
    "algo": "SMCO_BR",
    "time_avg": "0.636229593103053",
    "rMSE": "0.06107931383250387",
    "AE50": "0.057205857989596265",
    "AE95": "0.09324085513738192",
    "AE99": "0.09638154699430997",
    "fopt_mean": "0.08571570438391113",
    "fopt_sd": "0.023697623974425576"
  },
  {
    "label": "Griewank_10d",
    "name": "Griewank",
    "dim": "10",
    "maximize": "False",
    "repetitions": "20",
    "iter_max": "300",
    "n_starts": "10",
    "seed": "20260928",
    "evolution_strategy": "sobol",
    "best_opt": "0.029172056948342462",
    "algo": "SMCO_BR_EVO",
    "time_avg": "0.6475528180482797",
    "rMSE": "0.09253925870346325",
    "AE50": "0.095191275053986",
    "AE95": "0.12385303300036858",
    "AE99": "0.13400894242596945",
    "fopt_mean": "0.11751174760357345",
    "fopt_sd": "0.028277077499639494"
  },
  {
    "label": "Griewank_10d",
    "name": "Griewank",
    "dim": "10",
    "maximize": "False",
    "repetitions": "20",
    "iter_max": "300",
    "n_starts": "10",
    "seed": "20260928",
    "evolution_strategy": "sobol",
    "best_opt": "0.029172056948342462",
    "algo": "SMCO_EVO",
    "time_avg": "0.642445795450476",
    "rMSE": "0.37819965319628673",
    "AE50": "0.3808305677791574",
    "AE95": "0.4815083340146506",
    "AE99": "0.49182508350382514",
    "fopt_mean": "0.39489972568946075",
    "fopt_sd": "0.09882600336997627"
  },
  {
    "label": "Griewank_10d",
    "name": "Griewank",
    "dim": "10",
    "maximize": "False",
    "repetitions": "20",
    "iter_max": "300",
    "n_starts": "10",
    "seed": "20260928",
    "evolution_strategy": "sobol",
    "best_opt": "0.029172056948342462",
    "algo": "SMCO_R",
    "time_avg": "0.6427236861956771",
    "rMSE": "0.05350166917906918",
    "AE50": "0.05219005927556136",
    "AE95": "0.0708611808574442",
    "AE99": "0.07091010620648439",
    "fopt_mean": "0.08131047048231607",
    "fopt_sd": "0.01231235746834596"
  },
  {
    "label": "Griewank_10d",
    "name": "Griewank",
    "dim": "10",
    "maximize": "False",
    "repetitions": "20",
    "iter_max": "300",
    "n_starts": "10",
    "seed": "20260928",
    "evolution_strategy": "sobol",
    "best_opt": "0.029172056948342462",
    "algo": "SMCO_R_EVO",
    "time_avg": "0.6385148079047213",
    "rMSE": "0.056773120681718366",
    "AE50": "0.04621735006498506",
    "AE95": "0.0859035514979063",
    "AE99": "0.12672120836427206",
    "fopt_mean": "0.07949295105158834",
    "fopt_sd": "0.026969668120255166"
  },
  {
    "label": "McCormick_2d",
    "name": "McCormick",
    "dim": "2",
    "maximize": "False",
    "repetitions": "20",
    "iter_max": "300",
    "n_starts": "10",
    "seed": "20261728",
    "evolution_strategy": "sobol",
    "best_opt": "-1.9132229549696742",
    "algo": "SMCO",
    "time_avg": "0.07977723964431789",
    "rMSE": "3.106028675573544e-07",
    "AE50": "1.4814433568766106e-07",
    "AE95": "6.346528705236668e-07",
    "AE99": "8.958732258790287e-07",
    "fopt_mean": "-1.9132227453375588",
    "fopt_sd": "2.351450111039161e-07"
  },
  {
    "label": "McCormick_2d",
    "name": "McCormick",
    "dim": "2",
    "maximize": "False",
    "repetitions": "20",
    "iter_max": "300",
    "n_starts": "10",
    "seed": "20261728",
    "evolution_strategy": "sobol",
    "best_opt": "-1.9132229549696742",
    "algo": "SMCO_BR",
    "time_avg": "0.0898449528584024",
    "rMSE": "5.3539123514200426e-08",
    "AE50": "2.5240451506647332e-08",
    "AE95": "1.0775535939089314e-07",
    "AE99": "1.5439618456625217e-07",
    "fopt_mean": "-1.913222918956524",
    "fopt_sd": "4.06459783997552e-08"
  },
  {
    "label": "McCormick_2d",
    "name": "McCormick",
    "dim": "2",
    "maximize": "False",
    "repetitions": "20",
    "iter_max": "300",
    "n_starts": "10",
    "seed": "20261728",
    "evolution_strategy": "sobol",
    "best_opt": "-1.9132229549696742",
    "algo": "SMCO_BR_EVO",
    "time_avg": "0.08242319105193019",
    "rMSE": "5.448465174134005e-08",
    "AE50": "1.8838596460568624e-08",
    "AE95": "1.168229404768795e-07",
    "AE99": "1.6270389654238208e-07",
    "fopt_mean": "-1.9132229212616778",
    "fopt_sd": "4.3917964810897925e-08"
  },
  {
    "label": "McCormick_2d",
    "name": "McCormick",
    "dim": "2",
    "maximize": "False",
    "repetitions": "20",
    "iter_max": "300",
    "n_starts": "10",
    "seed": "20261728",
    "evolution_strategy": "sobol",
    "best_opt": "-1.9132229549696742",
    "algo": "SMCO_EVO",
    "time_avg": "0.08809824899362866",
    "rMSE": "2.627523973969035e-07",
    "AE50": "8.012642860322217e-08",
    "AE95": "6.342855929153403e-07",
    "AE99": "7.305435122573199e-07",
    "fopt_mean": "-1.9132227872037788",
    "fopt_sd": "2.0747460640197378e-07"
  },
  {
    "label": "McCormick_2d",
    "name": "McCormick",
    "dim": "2",
    "maximize": "False",
    "repetitions": "20",
    "iter_max": "300",
    "n_starts": "10",
    "seed": "20261728",
    "evolution_strategy": "sobol",
    "best_opt": "-1.9132229549696742",
    "algo": "SMCO_R",
    "time_avg": "0.07979708255152218",
    "rMSE": "2.9561654395202504e-08",
    "AE50": "1.417472983433754e-08",
    "AE95": "6.843457796001929e-08",
    "AE99": "6.898665904309098e-08",
    "fopt_mean": "-1.913222934970292",
    "fopt_sd": "2.2335153352620412e-08"
  },
  {
    "label": "McCormick_2d",
    "name": "McCormick",
    "dim": "2",
    "maximize": "False",
    "repetitions": "20",
    "iter_max": "300",
    "n_starts": "10",
    "seed": "20261728",
    "evolution_strategy": "sobol",
    "best_opt": "-1.9132229549696742",
    "algo": "SMCO_R_EVO",
    "time_avg": "0.08014010961051099",
    "rMSE": "3.282577621352037e-08",
    "AE50": "1.1166269242579574e-08",
    "AE95": "4.045468189328722e-08",
    "AE99": "1.0986939901425062e-07",
    "fopt_mean": "-1.9132229366712061",
    "fopt_sd": "2.7960454112581623e-08"
  },
  {
    "label": "Michalewicz_10d",
    "name": "Michalewicz",
    "dim": "10",
    "maximize": "False",
    "repetitions": "20",
    "iter_max": "300",
    "n_starts": "10",
    "seed": "20261428",
    "evolution_strategy": "sobol",
    "best_opt": "-9.311367538116851",
    "algo": "SMCO",
    "time_avg": "0.9894344664935488",
    "rMSE": "0.34662378096527224",
    "AE50": "0.3252055046082205",
    "AE95": "0.5186452400704121",
    "AE99": "0.5653464220436772",
    "fopt_mean": "-9.0061534916201",
    "fopt_sd": "0.16856181546664847"
  },
  {
    "label": "Michalewicz_10d",
    "name": "Michalewicz",
    "dim": "10",
    "maximize": "False",
    "repetitions": "20",
    "iter_max": "300",
    "n_starts": "10",
    "seed": "20261428",
    "evolution_strategy": "sobol",
    "best_opt": "-9.311367538116851",
    "algo": "SMCO_BR",
    "time_avg": "1.0213215498428325",
    "rMSE": "0.4055338884878698",
    "AE50": "0.3272439098729203",
    "AE95": "0.6481770944327756",
    "AE99": "0.8467551194393307",
    "fopt_mean": "-8.95630273736533",
    "fopt_sd": "0.2010151132819749"
  },
  {
    "label": "Michalewicz_10d",
    "name": "Michalewicz",
    "dim": "10",
    "maximize": "False",
    "repetitions": "20",
    "iter_max": "300",
    "n_starts": "10",
    "seed": "20261428",
    "evolution_strategy": "sobol",
    "best_opt": "-9.311367538116851",
    "algo": "SMCO_BR_EVO",
    "time_avg": "1.1063147180480883",
    "rMSE": "0.3687363433622402",
    "AE50": "0.28878868180006023",
    "AE95": "0.5007043857684134",
    "AE99": "0.7302392810921183",
    "fopt_mean": "-8.978093028015204",
    "fopt_sd": "0.16187907063010265"
  },
  {
    "label": "Michalewicz_10d",
    "name": "Michalewicz",
    "dim": "10",
    "maximize": "False",
    "repetitions": "20",
    "iter_max": "300",
    "n_starts": "10",
    "seed": "20261428",
    "evolution_strategy": "sobol",
    "best_opt": "-9.311367538116851",
    "algo": "SMCO_EVO",
    "time_avg": "1.0627974300587084",
    "rMSE": "0.3629145287545889",
    "AE50": "0.35100456741484454",
    "AE95": "0.522347201990796",
    "AE99": "0.566000451488193",
    "fopt_mean": "-8.976351360531538",
    "fopt_sd": "0.14316393230467625"
  },
  {
    "label": "Michalewicz_10d",
    "name": "Michalewicz",
    "dim": "10",
    "maximize": "False",
    "repetitions": "20",
    "iter_max": "300",
    "n_starts": "10",
    "seed": "20261428",
    "evolution_strategy": "sobol",
    "best_opt": "-9.311367538116851",
    "algo": "SMCO_R",
    "time_avg": "0.9930261842004257",
    "rMSE": "0.39180304656046705",
    "AE50": "0.3277258098229714",
    "AE95": "0.6193090522492843",
    "AE99": "0.8407915837306257",
    "fopt_mean": "-8.980431601924318",
    "fopt_sd": "0.21518910515963938"
  },
  {
    "label": "Michalewicz_10d",
    "name": "Michalewicz",
    "dim": "10",
    "maximize": "False",
    "repetitions": "20",
    "iter_max": "300",
    "n_starts": "10",
    "seed": "20261428",
    "evolution_strategy": "sobol",
    "best_opt": "-9.311367538116851",
    "algo": "SMCO_R_EVO",
    "time_avg": "1.0768106486473699",
    "rMSE": "0.33573990912534507",
    "AE50": "0.3048279176865245",
    "AE95": "0.4943956989030646",
    "AE99": "0.6318387751722229",
    "fopt_mean": "-9.019823016158472",
    "fopt_sd": "0.17082794759503384"
  },
  {
    "label": "Mishra6_2d",
    "name": "Mishra6",
    "dim": "2",
    "maximize": "False",
    "repetitions": "20",
    "iter_max": "300",
    "n_starts": "10",
    "seed": "20262228",
    "evolution_strategy": "sobol",
    "best_opt": "-3.962707721644123",
    "algo": "SMCO",
    "time_avg": "0.12858480125141797",
    "rMSE": "0.10171652972653676",
    "AE50": "0.04213632559950842",
    "AE95": "0.124557118125931",
    "AE99": "0.3118158323058515",
    "fopt_mean": "-3.901533733152564",
    "fopt_sd": "0.0833761012814137"
  },
  {
    "label": "Mishra6_2d",
    "name": "Mishra6",
    "dim": "2",
    "maximize": "False",
    "repetitions": "20",
    "iter_max": "300",
    "n_starts": "10",
    "seed": "20262228",
    "evolution_strategy": "sobol",
    "best_opt": "-3.962707721644123",
    "algo": "SMCO_BR",
    "time_avg": "0.13108683049795217",
    "rMSE": "0.09562506850690689",
    "AE50": "0.00021395512520316906",
    "AE95": "0.1152479924142682",
    "AE99": "0.30995389435621695",
    "fopt_mean": "-3.912628337389383",
    "fopt_sd": "0.08357920290054971"
  },
  {
    "label": "Mishra6_2d",
    "name": "Mishra6",
    "dim": "2",
    "maximize": "False",
    "repetitions": "20",
    "iter_max": "300",
    "n_starts": "10",
    "seed": "20262228",
    "evolution_strategy": "sobol",
    "best_opt": "-3.962707721644123",
    "algo": "SMCO_BR_EVO",
    "time_avg": "0.1330025629431475",
    "rMSE": "0.09535732308863672",
    "AE50": "0.0015887893596024938",
    "AE95": "0.11524875559116575",
    "AE99": "0.3099540980236785",
    "fopt_mean": "-3.9128431723270873",
    "fopt_sd": "0.08339219822172889"
  },
  {
    "label": "Mishra6_2d",
    "name": "Mishra6",
    "dim": "2",
    "maximize": "False",
    "repetitions": "20",
    "iter_max": "300",
    "n_starts": "10",
    "seed": "20262228",
    "evolution_strategy": "sobol",
    "best_opt": "-3.962707721644123",
    "algo": "SMCO_EVO",
    "time_avg": "0.13034899135236627",
    "rMSE": "0.09730021703535492",
    "AE50": "0.04042633648412686",
    "AE95": "0.11526000023905697",
    "AE99": "0.3099564102131085",
    "fopt_mean": "-3.9078245491149155",
    "fopt_sd": "0.08243127669223654"
  },
  {
    "label": "Mishra6_2d",
    "name": "Mishra6",
    "dim": "2",
    "maximize": "False",
    "repetitions": "20",
    "iter_max": "300",
    "n_starts": "10",
    "seed": "20262228",
    "evolution_strategy": "sobol",
    "best_opt": "-3.962707721644123",
    "algo": "SMCO_R",
    "time_avg": "0.12936614530044607",
    "rMSE": "0.09492783772181283",
    "AE50": "0.0027510467028486474",
    "AE95": "0.11524540208836792",
    "AE99": "0.3099533518900174",
    "fopt_mean": "-3.912951264373439",
    "fopt_sd": "0.08294315957588716"
  },
  {
    "label": "Mishra6_2d",
    "name": "Mishra6",
    "dim": "2",
    "maximize": "False",
    "repetitions": "20",
    "iter_max": "300",
    "n_starts": "10",
    "seed": "20262228",
    "evolution_strategy": "sobol",
    "best_opt": "-3.962707721644123",
    "algo": "SMCO_R_EVO",
    "time_avg": "0.12910671449790243",
    "rMSE": "0.04948920559302985",
    "AE50": "0.00017281124636170375",
    "AE95": "0.10243591140927535",
    "AE99": "0.10243625282258549",
    "fopt_mean": "-3.932659678485944",
    "fopt_sd": "0.04034452382579136"
  },
  {
    "label": "NegativeSquaredNorm_10d",
    "name": "NegativeSquaredNorm",
    "dim": "10",
    "maximize": "True",
    "repetitions": "20",
    "iter_max": "300",
    "n_starts": "10",
    "seed": "20260628",
    "evolution_strategy": "sobol",
    "best_opt": "-4.0373592735600385e-07",
    "algo": "SMCO",
    "time_avg": "0.30937151005491614",
    "rMSE": "1.3908809213111448e-05",
    "AE50": "1.2770930157543766e-05",
    "AE95": "1.8963243899418794e-05",
    "AE99": "1.9552146788266426e-05",
    "fopt_mean": "-1.3879409908888125e-05",
    "fopt_sd": "3.5334766642846685e-06"
  },
  {
    "label": "NegativeSquaredNorm_10d",
    "name": "NegativeSquaredNorm",
    "dim": "10",
    "maximize": "True",
    "repetitions": "20",
    "iter_max": "300",
    "n_starts": "10",
    "seed": "20260628",
    "evolution_strategy": "sobol",
    "best_opt": "-4.0373592735600385e-07",
    "algo": "SMCO_BR",
    "time_avg": "0.3158041451504687",
    "rMSE": "9.62032353290124e-07",
    "AE50": "9.668199088569627e-07",
    "AE95": "1.3329767879133846e-06",
    "AE99": "1.344864248877488e-06",
    "fopt_mean": "-1.3012107131092039e-06",
    "fopt_sd": "3.554763412279677e-07"
  },
  {
    "label": "NegativeSquaredNorm_10d",
    "name": "NegativeSquaredNorm",
    "dim": "10",
    "maximize": "True",
    "repetitions": "20",
    "iter_max": "300",
    "n_starts": "10",
    "seed": "20260628",
    "evolution_strategy": "sobol",
    "best_opt": "-4.0373592735600385e-07",
    "algo": "SMCO_BR_EVO",
    "time_avg": "0.3210707587597426",
    "rMSE": "1.0951612360868813e-06",
    "AE50": "1.0505563009691535e-06",
    "AE95": "1.4200314747579748e-06",
    "AE99": "1.7404205602401594e-06",
    "fopt_mean": "-1.4427544107130615e-06",
    "fopt_sd": "3.551407790095663e-07"
  },
  {
    "label": "NegativeSquaredNorm_10d",
    "name": "NegativeSquaredNorm",
    "dim": "10",
    "maximize": "True",
    "repetitions": "20",
    "iter_max": "300",
    "n_starts": "10",
    "seed": "20260628",
    "evolution_strategy": "sobol",
    "best_opt": "-4.0373592735600385e-07",
    "algo": "SMCO_EVO",
    "time_avg": "0.3086732665484305",
    "rMSE": "1.558256703637479e-05",
    "AE50": "1.5843745657684046e-05",
    "AE95": "1.982794255852623e-05",
    "AE99": "2.0681929767726267e-05",
    "fopt_mean": "-1.564189260253763e-05",
    "fopt_sd": "3.3427024342481187e-06"
  },
  {
    "label": "NegativeSquaredNorm_10d",
    "name": "NegativeSquaredNorm",
    "dim": "10",
    "maximize": "True",
    "repetitions": "20",
    "iter_max": "300",
    "n_starts": "10",
    "seed": "20260628",
    "evolution_strategy": "sobol",
    "best_opt": "-4.0373592735600385e-07",
    "algo": "SMCO_R",
    "time_avg": "0.316125281053246",
    "rMSE": "8.259661159585616e-07",
    "AE50": "8.169396758297433e-07",
    "AE95": "1.18096639231991e-06",
    "AE99": "1.2576958581683269e-06",
    "fopt_mean": "-1.1641967177891593e-06",
    "fopt_sd": "3.3073985790306547e-07"
  },
  {
    "label": "NegativeSquaredNorm_10d",
    "name": "NegativeSquaredNorm",
    "dim": "10",
    "maximize": "True",
    "repetitions": "20",
    "iter_max": "300",
    "n_starts": "10",
    "seed": "20260628",
    "evolution_strategy": "sobol",
    "best_opt": "-4.0373592735600385e-07",
    "algo": "SMCO_R_EVO",
    "time_avg": "0.31429474309843497",
    "rMSE": "9.489920259386002e-07",
    "AE50": "9.043033717102057e-07",
    "AE95": "1.3828421839096356e-06",
    "AE99": "1.4344198297081105e-06",
    "fopt_mean": "-1.311600155131767e-06",
    "fopt_sd": "2.835274222700911e-07"
  },
  {
    "label": "Qing_10d",
    "name": "Qing",
    "dim": 10,
    "maximize": false,
    "repetitions": 20,
    "iter_max": 300,
    "n_starts": 10,
    "seed": 20261328,
    "evolution_strategy": "sobol",
    "best_opt": 2.350808736294278,
    "algo": "SMCO",
    "time_avg": 0.5011435508029536,
    "rMSE": 57.08544181767567,
    "AE50": 49.5575831047061,
    "AE95": 91.78604686952676,
    "AE99": 99.23153855785564,
    "fopt_mean": 56.387585944634836,
    "fopt_sd": 18.883977515215328
  },
  {
    "label": "Qing_10d",
    "name": "Qing",
    "dim": 10,
    "maximize": false,
    "repetitions": 20,
    "iter_max": 300,
    "n_starts": 10,
    "seed": 20261328,
    "evolution_strategy": "sobol",
    "best_opt": 2.350808736294278,
    "algo": "SMCO_BR",
    "time_avg": 0.5313644113019109,
    "rMSE": 3.6987550581577584,
    "AE50": 3.543275407401193,
    "AE95": 5.615987495050675,
    "AE99": 6.561389086034929,
    "fopt_mean": 5.700587202687324,
    "fopt_sd": 1.6091099881732753
  },
  {
    "label": "Qing_10d",
    "name": "Qing",
    "dim": 10,
    "maximize": false,
    "repetitions": 20,
    "iter_max": 300,
    "n_starts": 10,
    "seed": 20261328,
    "evolution_strategy": "sobol",
    "best_opt": 2.350808736294278,
    "algo": "SMCO_BR_EVO",
    "time_avg": 0.5161544742994011,
    "rMSE": 4.400222180090714,
    "AE50": 3.662740297805022,
    "AE95": 7.601182599485692,
    "AE99": 8.272224452265295,
    "fopt_mean": 6.261788387702007,
    "fopt_sd": 2.068865287883026
  },
  {
    "label": "Qing_10d",
    "name": "Qing",
    "dim": 10,
    "maximize": false,
    "repetitions": 20,
    "iter_max": 300,
    "n_starts": 10,
    "seed": 20261328,
    "evolution_strategy": "sobol",
    "best_opt": 2.350808736294278,
    "algo": "SMCO_EVO",
    "time_avg": 0.5292403422994539,
    "rMSE": 60.543582014558794,
    "AE50": 57.41401505231523,
    "AE95": 82.35993926594539,
    "AE99": 83.55353997789418,
    "fopt_mean": 60.89990753817742,
    "fopt_sd": 15.812332050813692
  },
  {
    "label": "Qing_10d",
    "name": "Qing",
    "dim": 10,
    "maximize": false,
    "repetitions": 20,
    "iter_max": 300,
    "n_starts": 10,
    "seed": 20261328,
    "evolution_strategy": "sobol",
    "best_opt": 2.350808736294278,
    "algo": "SMCO_R",
    "time_avg": 0.5054085524490801,
    "rMSE": 2.6549549365311664,
    "AE50": 2.332360525329413,
    "AE95": 3.984854452330015,
    "AE99": 5.582158232592831,
    "fopt_mean": 4.688329947966521,
    "fopt_sd": 1.2915842169471103
  },
  {
    "label": "Qing_10d",
    "name": "Qing",
    "dim": 10,
    "maximize": false,
    "repetitions": 20,
    "iter_max": 300,
    "n_starts": 10,
    "seed": 20261328,
    "evolution_strategy": "sobol",
    "best_opt": 2.350808736294278,
    "algo": "SMCO_R_EVO",
    "time_avg": 0.5179475950513733,
    "rMSE": 3.237056744667525,
    "AE50": 3.038277489022078,
    "AE95": 4.926332649807631,
    "AE99": 5.305184188428298,
    "fopt_mean": 5.336767336151132,
    "fopt_sd": 1.2825088932238757
  },
  {
    "label": "Rastrigin_10d",
    "name": "Rastrigin",
    "dim": "10",
    "maximize": "False",
    "repetitions": "20",
    "iter_max": "300",
    "n_starts": "10",
    "seed": "20260728",
    "evolution_strategy": "sobol",
    "best_opt": "1.0083458593917385",
    "algo": "SMCO",
    "time_avg": "0.49591838763735724",
    "rMSE": "3.123450912816894",
    "AE50": "3.0710563089962974",
    "AE95": "4.069223430131334",
    "AE99": "4.073522481573321",
    "fopt_mean": "4.029380060225913",
    "fopt_sd": "0.8138912135808526"
  },
  {
    "label": "Rastrigin_10d",
    "name": "Rastrigin",
    "dim": "10",
    "maximize": "False",
    "repetitions": "20",
    "iter_max": "300",
    "n_starts": "10",
    "seed": "20260728",
    "evolution_strategy": "sobol",
    "best_opt": "1.0083458593917385",
    "algo": "SMCO_BR",
    "time_avg": "0.5034611830400536",
    "rMSE": "3.1018089987158715",
    "AE50": "2.9801095173979704",
    "AE95": "4.0262462132033985",
    "AE99": "4.777776254797237",
    "fopt_mean": "3.938527972867606",
    "fopt_sd": "1.0439055444167626"
  },
  {
    "label": "Rastrigin_10d",
    "name": "Rastrigin",
    "dim": "10",
    "maximize": "False",
    "repetitions": "20",
    "iter_max": "300",
    "n_starts": "10",
    "seed": "20260728",
    "evolution_strategy": "sobol",
    "best_opt": "1.0083458593917385",
    "algo": "SMCO_BR_EVO",
    "time_avg": "0.5173924162518233",
    "rMSE": "2.997084617632109",
    "AE50": "2.9816805398987256",
    "AE95": "3.975244998458531",
    "AE99": "3.9752680388302757",
    "fopt_mean": "3.7899647275319666",
    "fopt_sd": "1.144834015849266"
  },
  {
    "label": "Rastrigin_10d",
    "name": "Rastrigin",
    "dim": "10",
    "maximize": "False",
    "repetitions": "20",
    "iter_max": "300",
    "n_starts": "10",
    "seed": "20260728",
    "evolution_strategy": "sobol",
    "best_opt": "1.0083458593917385",
    "algo": "SMCO_EVO",
    "time_avg": "0.4985303352528717",
    "rMSE": "3.1994922414159896",
    "AE50": "3.0612496944238146",
    "AE95": "4.131912900355219",
    "AE99": "4.8442664316455355",
    "fopt_mean": "4.123786245999284",
    "fopt_sd": "0.7474742033047302"
  },
  {
    "label": "Rastrigin_10d",
    "name": "Rastrigin",
    "dim": "10",
    "maximize": "False",
    "repetitions": "20",
    "iter_max": "300",
    "n_starts": "10",
    "seed": "20260728",
    "evolution_strategy": "sobol",
    "best_opt": "1.0083458593917385",
    "algo": "SMCO_R",
    "time_avg": "0.5035021329007577",
    "rMSE": "3.404874245148374",
    "AE50": "2.9819233432540813",
    "AE95": "4.967704509043363",
    "AE99": "4.967965467469629",
    "fopt_mean": "4.236164823434865",
    "fopt_sd": "1.1118279688201795"
  },
  {
    "label": "Rastrigin_10d",
    "name": "Rastrigin",
    "dim": "10",
    "maximize": "False",
    "repetitions": "20",
    "iter_max": "300",
    "n_starts": "10",
    "seed": "20260728",
    "evolution_strategy": "sobol",
    "best_opt": "1.0083458593917385",
    "algo": "SMCO_R_EVO",
    "time_avg": "0.5026316915056668",
    "rMSE": "3.225821969461871",
    "AE50": "2.9808100690670685",
    "AE95": "3.9743125703298134",
    "AE99": "3.974490835306679",
    "fopt_mean": "4.13651250174145",
    "fopt_sd": "0.8081823897542194"
  },
  {
    "label": "Rosenbrock_10d",
    "name": "Rosenbrock",
    "dim": "10",
    "maximize": "False",
    "repetitions": "20",
    "iter_max": "300",
    "n_starts": "10",
    "seed": "20261028",
    "evolution_strategy": "sobol",
    "best_opt": "0.010095462887883558",
    "algo": "SMCO",
    "time_avg": "0.6159700504009379",
    "rMSE": "0.8899570808774602",
    "AE50": "0.8891914237742469",
    "AE95": "1.1332654047303576",
    "AE99": "1.2282632340097066",
    "fopt_mean": "0.8608068451187403",
    "fopt_sd": "0.2681589276349205"
  },
  {
    "label": "Rosenbrock_10d",
    "name": "Rosenbrock",
    "dim": "10",
    "maximize": "False",
    "repetitions": "20",
    "iter_max": "300",
    "n_starts": "10",
    "seed": "20261028",
    "evolution_strategy": "sobol",
    "best_opt": "0.010095462887883558",
    "algo": "SMCO_BR",
    "time_avg": "0.614982851097011",
    "rMSE": "0.17024341790558467",
    "AE50": "0.09681701469254853",
    "AE95": "0.36274395901485756",
    "AE99": "0.36310242634820133",
    "fopt_mean": "0.14417887704854107",
    "fopt_sd": "0.10762732673539514"
  },
  {
    "label": "Rosenbrock_10d",
    "name": "Rosenbrock",
    "dim": "10",
    "maximize": "False",
    "repetitions": "20",
    "iter_max": "300",
    "n_starts": "10",
    "seed": "20261028",
    "evolution_strategy": "sobol",
    "best_opt": "0.010095462887883558",
    "algo": "SMCO_BR_EVO",
    "time_avg": "0.6040153522480978",
    "rMSE": "0.24341759266342006",
    "AE50": "0.19493600547875148",
    "AE95": "0.38488981042244796",
    "AE99": "0.4464538429938495",
    "fopt_mean": "0.22130369248148107",
    "fopt_sd": "0.1241527419626108"
  },
  {
    "label": "Rosenbrock_10d",
    "name": "Rosenbrock",
    "dim": "10",
    "maximize": "False",
    "repetitions": "20",
    "iter_max": "300",
    "n_starts": "10",
    "seed": "20261028",
    "evolution_strategy": "sobol",
    "best_opt": "0.010095462887883558",
    "algo": "SMCO_EVO",
    "time_avg": "0.6028273556585191",
    "rMSE": "0.914608300121691",
    "AE50": "0.9167708726303405",
    "AE95": "1.1523529675474997",
    "AE99": "1.3645299858680715",
    "fopt_mean": "0.8953688585782367",
    "fopt_sd": "0.23575044239364895"
  },
  {
    "label": "Rosenbrock_10d",
    "name": "Rosenbrock",
    "dim": "10",
    "maximize": "False",
    "repetitions": "20",
    "iter_max": "300",
    "n_starts": "10",
    "seed": "20261028",
    "evolution_strategy": "sobol",
    "best_opt": "0.010095462887883558",
    "algo": "SMCO_R",
    "time_avg": "0.6069583684497047",
    "rMSE": "0.1987813608447487",
    "AE50": "0.07490174831887803",
    "AE95": "0.43315694796897974",
    "AE99": "0.5123494458002289",
    "fopt_mean": "0.14191498450258122",
    "fopt_sd": "0.15265248852614105"
  },
  {
    "label": "Rosenbrock_10d",
    "name": "Rosenbrock",
    "dim": "10",
    "maximize": "False",
    "repetitions": "20",
    "iter_max": "300",
    "n_starts": "10",
    "seed": "20261028",
    "evolution_strategy": "sobol",
    "best_opt": "0.010095462887883558",
    "algo": "SMCO_R_EVO",
    "time_avg": "0.6175073984457413",
    "rMSE": "0.2699687914991093",
    "AE50": "0.11199363617685537",
    "AE95": "0.5238347750096513",
    "AE99": "0.5645098096437229",
    "fopt_mean": "0.21374990726049536",
    "fopt_sd": "0.1818270307933579"
  },
  {
    "label": "Shubert_2d",
    "name": "Shubert",
    "dim": "2",
    "maximize": "False",
    "repetitions": "20",
    "iter_max": "300",
    "n_starts": "10",
    "seed": "20261628",
    "evolution_strategy": "sobol",
    "best_opt": "-186.73090426335588",
    "algo": "SMCO",
    "time_avg": "0.2711600616457872",
    "rMSE": "39.3309427734785",
    "AE50": "0.005558739364147414",
    "AE95": "106.73578789254614",
    "AE99": "118.38491183504439",
    "fopt_mean": "-169.67517476831728",
    "fopt_sd": "36.3611294891835"
  },
  {
    "label": "Shubert_2d",
    "name": "Shubert",
    "dim": "2",
    "maximize": "False",
    "repetitions": "20",
    "iter_max": "300",
    "n_starts": "10",
    "seed": "20261628",
    "evolution_strategy": "sobol",
    "best_opt": "-186.73090426335588",
    "algo": "SMCO_BR",
    "time_avg": "0.2753372047445737",
    "rMSE": "14.471128934349316",
    "AE50": "0.00035319230953234637",
    "AE95": "16.585076440266953",
    "AE99": "53.84067356168698",
    "fopt_mean": "-182.86615447305442",
    "fopt_sd": "14.307792565515392"
  },
  {
    "label": "Shubert_2d",
    "name": "Shubert",
    "dim": "2",
    "maximize": "False",
    "repetitions": "20",
    "iter_max": "300",
    "n_starts": "10",
    "seed": "20261628",
    "evolution_strategy": "sobol",
    "best_opt": "-186.73090426335588",
    "algo": "SMCO_BR_EVO",
    "time_avg": "0.29084527138620614",
    "rMSE": "20.219813628658617",
    "AE50": "0.0002241571404795195",
    "AE95": "63.154468190605336",
    "AE99": "63.15495073699673",
    "fopt_mean": "-179.70849666029187",
    "fopt_sd": "19.45376853314484"
  },
  {
    "label": "Shubert_2d",
    "name": "Shubert",
    "dim": "2",
    "maximize": "False",
    "repetitions": "20",
    "iter_max": "300",
    "n_starts": "10",
    "seed": "20261628",
    "evolution_strategy": "sobol",
    "best_opt": "-186.73090426335588",
    "algo": "SMCO_EVO",
    "time_avg": "0.27909572470234706",
    "rMSE": "20.68649071713054",
    "AE50": "0.0033277891154028794",
    "AE95": "53.56362760603342",
    "AE99": "71.23969139638687",
    "fopt_mean": "-179.74609392748476",
    "fopt_sd": "19.97744314185735"
  },
  {
    "label": "Shubert_2d",
    "name": "Shubert",
    "dim": "2",
    "maximize": "False",
    "repetitions": "20",
    "iter_max": "300",
    "n_starts": "10",
    "seed": "20261628",
    "evolution_strategy": "sobol",
    "best_opt": "-186.73090426335588",
    "algo": "SMCO_R",
    "time_avg": "0.27882238700403833",
    "rMSE": "20.04182654951018",
    "AE50": "0.00021068668526424972",
    "AE95": "63.154154930728595",
    "AE99": "63.15447275792878",
    "fopt_mean": "-180.03930183220484",
    "fopt_sd": "19.382500744202623"
  },
  {
    "label": "Shubert_2d",
    "name": "Shubert",
    "dim": "2",
    "maximize": "False",
    "repetitions": "20",
    "iter_max": "300",
    "n_starts": "10",
    "seed": "20261628",
    "evolution_strategy": "sobol",
    "best_opt": "-186.73090426335588",
    "algo": "SMCO_R_EVO",
    "time_avg": "0.27042441919911653",
    "rMSE": "14.221505019645328",
    "AE50": "8.704695956396336e-05",
    "AE95": "10.301951606607396",
    "AE99": "52.58385801853212",
    "fopt_mean": "-183.19706666798476",
    "fopt_sd": "14.133319976243486"
  },
  {
    "label": "SixHumpCamel_2d",
    "name": "SixHumpCamel",
    "dim": "2",
    "maximize": "False",
    "repetitions": "20",
    "iter_max": "300",
    "n_starts": "10",
    "seed": "20261828",
    "evolution_strategy": "sobol",
    "best_opt": "-1.0316284533856406",
    "algo": "SMCO",
    "time_avg": "0.08416884419857525",
    "rMSE": "1.0277628881471432e-06",
    "AE50": "3.140521079858516e-07",
    "AE95": "2.1658361525567217e-06",
    "AE99": "2.3007057292900865e-06",
    "fopt_mean": "-1.0316277474730853",
    "fopt_sd": "7.663886730950211e-07"
  },
  {
    "label": "SixHumpCamel_2d",
    "name": "SixHumpCamel",
    "dim": "2",
    "maximize": "False",
    "repetitions": "20",
    "iter_max": "300",
    "n_starts": "10",
    "seed": "20261828",
    "evolution_strategy": "sobol",
    "best_opt": "-1.0316284533856406",
    "algo": "SMCO_BR",
    "time_avg": "0.086215149142663",
    "rMSE": "6.381366398096429e-08",
    "AE50": "2.9696702541492925e-08",
    "AE95": "1.2857255100584557e-07",
    "AE99": "1.6289094752153226e-07",
    "fopt_mean": "-1.0316284084169658",
    "fopt_sd": "4.6453168073725615e-08"
  },
  {
    "label": "SixHumpCamel_2d",
    "name": "SixHumpCamel",
    "dim": "2",
    "maximize": "False",
    "repetitions": "20",
    "iter_max": "300",
    "n_starts": "10",
    "seed": "20261828",
    "evolution_strategy": "sobol",
    "best_opt": "-1.0316284533856406",
    "algo": "SMCO_BR_EVO",
    "time_avg": "0.0948871920525562",
    "rMSE": "5.568043322738097e-08",
    "AE50": "1.4826455840832864e-08",
    "AE95": "1.1653846023751416e-07",
    "AE99": "1.5670897637765072e-07",
    "fopt_mean": "-1.031628417572889",
    "fopt_sd": "4.37427583878392e-08"
  },
  {
    "label": "SixHumpCamel_2d",
    "name": "SixHumpCamel",
    "dim": "2",
    "maximize": "False",
    "repetitions": "20",
    "iter_max": "300",
    "n_starts": "10",
    "seed": "20261828",
    "evolution_strategy": "sobol",
    "best_opt": "-1.0316284533856406",
    "algo": "SMCO_EVO",
    "time_avg": "0.08670422075374518",
    "rMSE": "8.408434335141854e-07",
    "AE50": "4.1215141499684194e-07",
    "AE95": "1.6129071552573041e-06",
    "AE99": "1.898372934201475e-06",
    "fopt_mean": "-1.0316278239700685",
    "fopt_sd": "5.720266067445078e-07"
  },
  {
    "label": "SixHumpCamel_2d",
    "name": "SixHumpCamel",
    "dim": "2",
    "maximize": "False",
    "repetitions": "20",
    "iter_max": "300",
    "n_starts": "10",
    "seed": "20261828",
    "evolution_strategy": "sobol",
    "best_opt": "-1.0316284533856406",
    "algo": "SMCO_R",
    "time_avg": "0.08707231135340407",
    "rMSE": "3.347859367557344e-08",
    "AE50": "1.4535068593168887e-08",
    "AE95": "7.564735097220778e-08",
    "AE99": "9.914008643585599e-08",
    "fopt_mean": "-1.0316284313012833",
    "fopt_sd": "2.5815078995812175e-08"
  },
  {
    "label": "SixHumpCamel_2d",
    "name": "SixHumpCamel",
    "dim": "2",
    "maximize": "False",
    "repetitions": "20",
    "iter_max": "300",
    "n_starts": "10",
    "seed": "20261828",
    "evolution_strategy": "sobol",
    "best_opt": "-1.0316284533856406",
    "algo": "SMCO_R_EVO",
    "time_avg": "0.08821735810197424",
    "rMSE": "3.5303941295201227e-08",
    "AE50": "1.2964295637019063e-08",
    "AE95": "6.531203550208531e-08",
    "AE99": "6.656076289024426e-08",
    "fopt_mean": "-1.0316284269107774",
    "fopt_sd": "2.3961589658462523e-08"
  },
  {
    "label": "SquaredNorm_10d",
    "name": "SquaredNorm",
    "dim": "10",
    "maximize": "True",
    "repetitions": "20",
    "iter_max": "300",
    "n_starts": "10",
    "seed": "20260528",
    "evolution_strategy": "sobol",
    "best_opt": "9.833491784996816",
    "algo": "SMCO",
    "time_avg": "0.3128964464063756",
    "rMSE": "0.058857477822342665",
    "AE50": "0.04776915599227394",
    "AE95": "0.10490244914883312",
    "AE99": "0.11360755739924894",
    "fopt_mean": "9.782761545965208",
    "fopt_sd": "0.03061897491157026"
  },
  {
    "label": "SquaredNorm_10d",
    "name": "SquaredNorm",
    "dim": "10",
    "maximize": "True",
    "repetitions": "20",
    "iter_max": "300",
    "n_starts": "10",
    "seed": "20260528",
    "evolution_strategy": "sobol",
    "best_opt": "9.833491784996816",
    "algo": "SMCO_BR",
    "time_avg": "0.31275668449525257",
    "rMSE": "0.5925126204841188",
    "AE50": "0.5997925666417379",
    "AE95": "0.6910595815463536",
    "AE99": "0.7046538786374722",
    "fopt_mean": "9.24686388059496",
    "fopt_sd": "0.08546410271380622"
  },
  {
    "label": "SquaredNorm_10d",
    "name": "SquaredNorm",
    "dim": "10",
    "maximize": "True",
    "repetitions": "20",
    "iter_max": "300",
    "n_starts": "10",
    "seed": "20260528",
    "evolution_strategy": "sobol",
    "best_opt": "9.833491784996816",
    "algo": "SMCO_BR_EVO",
    "time_avg": "0.3221358959010104",
    "rMSE": "0.5935332423542296",
    "AE50": "0.593494190859988",
    "AE95": "0.7162086588589645",
    "AE99": "0.754423961517184",
    "fopt_mean": "9.245796035622387",
    "fopt_sd": "0.085195848346795"
  },
  {
    "label": "SquaredNorm_10d",
    "name": "SquaredNorm",
    "dim": "10",
    "maximize": "True",
    "repetitions": "20",
    "iter_max": "300",
    "n_starts": "10",
    "seed": "20260528",
    "evolution_strategy": "sobol",
    "best_opt": "9.833491784996816",
    "algo": "SMCO_EVO",
    "time_avg": "0.3181391736085061",
    "rMSE": "0.06863336018048227",
    "AE50": "0.056503077285555925",
    "AE95": "0.10885105714639727",
    "AE99": "0.13169804920222133",
    "fopt_mean": "9.772738914462362",
    "fopt_sd": "0.032761126699469886"
  },
  {
    "label": "SquaredNorm_10d",
    "name": "SquaredNorm",
    "dim": "10",
    "maximize": "True",
    "repetitions": "20",
    "iter_max": "300",
    "n_starts": "10",
    "seed": "20260528",
    "evolution_strategy": "sobol",
    "best_opt": "9.833491784996816",
    "algo": "SMCO_R",
    "time_avg": "0.3115335948532447",
    "rMSE": "0.2108370366589646",
    "AE50": "0.211397743493694",
    "AE95": "0.2728486528409612",
    "AE99": "0.2760199047172388",
    "fopt_mean": "9.62766975492723",
    "fopt_sd": "0.046899085000237976"
  },
  {
    "label": "SquaredNorm_10d",
    "name": "SquaredNorm",
    "dim": "10",
    "maximize": "True",
    "repetitions": "20",
    "iter_max": "300",
    "n_starts": "10",
    "seed": "20260528",
    "evolution_strategy": "sobol",
    "best_opt": "9.833491784996816",
    "algo": "SMCO_R_EVO",
    "time_avg": "0.3203728826076258",
    "rMSE": "0.20974141015237735",
    "AE50": "0.1972600418355226",
    "AE95": "0.2833680182319566",
    "AE99": "0.30746151585160725",
    "fopt_mean": "9.629973263470312",
    "fopt_sd": "0.0520290458187966"
  },
  {
    "label": "Zakharov_10d",
    "name": "Zakharov",
    "dim": 10,
    "maximize": false,
    "repetitions": 20,
    "iter_max": 300,
    "n_starts": 10,
    "seed": 20261228,
    "evolution_strategy": "sobol",
    "best_opt": 0.0016812920824312758,
    "algo": "SMCO",
    "time_avg": 0.8986333281529368,
    "rMSE": 0.04227468394527042,
    "AE50": 0.035165497349808374,
    "AE95": 0.07427444447775702,
    "AE99": 0.09037062930325246,
    "fopt_mean": 0.03739972192892581,
    "fopt_sd": 0.023200332846377184
  },
  {
    "label": "Zakharov_10d",
    "name": "Zakharov",
    "dim": 10,
    "maximize": false,
    "repetitions": 20,
    "iter_max": 300,
    "n_starts": 10,
    "seed": 20261228,
    "evolution_strategy": "sobol",
    "best_opt": 0.0016812920824312758,
    "algo": "SMCO_BR",
    "time_avg": 1.0371008017507848,
    "rMSE": 0.07088394914220864,
    "AE50": 0.05187264844884401,
    "AE95": 0.10148578079159404,
    "AE99": 0.1535353573319256,
    "fopt_mean": 0.06434400904195113,
    "fopt_sd": 0.03399563670526161
  },
  {
    "label": "Zakharov_10d",
    "name": "Zakharov",
    "dim": 10,
    "maximize": false,
    "repetitions": 20,
    "iter_max": 300,
    "n_starts": 10,
    "seed": 20261228,
    "evolution_strategy": "sobol",
    "best_opt": 0.0016812920824312758,
    "algo": "SMCO_BR_EVO",
    "time_avg": 0.9138115720474161,
    "rMSE": 0.06873695416822911,
    "AE50": 0.06021949587447805,
    "AE95": 0.10077763406624955,
    "AE99": 0.13876542728780894,
    "fopt_mean": 0.06444656901260132,
    "fopt_sd": 0.028750997789629085
  },
  {
    "label": "Zakharov_10d",
    "name": "Zakharov",
    "dim": 10,
    "maximize": false,
    "repetitions": 20,
    "iter_max": 300,
    "n_starts": 10,
    "seed": 20261228,
    "evolution_strategy": "sobol",
    "best_opt": 0.0016812920824312758,
    "algo": "SMCO_EVO",
    "time_avg": 0.9736091051046969,
    "rMSE": 0.0423536437387444,
    "AE50": 0.04365286286781137,
    "AE95": 0.06080489913187092,
    "AE99": 0.07969100161651609,
    "fopt_mean": 0.038924488176239204,
    "fopt_sd": 0.020692624739178867
  },
  {
    "label": "Zakharov_10d",
    "name": "Zakharov",
    "dim": 10,
    "maximize": false,
    "repetitions": 20,
    "iter_max": 300,
    "n_starts": 10,
    "seed": 20261228,
    "evolution_strategy": "sobol",
    "best_opt": 0.0016812920824312758,
    "algo": "SMCO_R",
    "time_avg": 0.9484176055964781,
    "rMSE": 0.029912383323933,
    "AE50": 0.02579914526557687,
    "AE95": 0.04544510956328663,
    "AE99": 0.048385808978642024,
    "fopt_mean": 0.030018830926590218,
    "fopt_sd": 0.00982663236064374
  },
  {
    "label": "Zakharov_10d",
    "name": "Zakharov",
    "dim": 10,
    "maximize": false,
    "repetitions": 20,
    "iter_max": 300,
    "n_starts": 10,
    "seed": 20261228,
    "evolution_strategy": "sobol",
    "best_opt": 0.0016812920824312758,
    "algo": "SMCO_R_EVO",
    "time_avg": 0.9755433876038296,
    "rMSE": 0.03647399023390299,
    "AE50": 0.03511190339305355,
    "AE95": 0.05331989106798497,
    "AE99": 0.060360442952046116,
    "fopt_mean": 0.03578189201120597,
    "fopt_sd": 0.01327843713380149
  }
]