[
  {
    "label": "table3_MaximumScore_d50",
    "name": "MaximumScore",
    "dim": 50,
    "maximize": true,
    "n_replications": 10,
    "best_opt": 0.482,
    "algo": "SMCO_EVO",
    "time_avg": 1.846068094210932,
    "rMSE": 0.06481975007665486,
    "AE50": 0.064,
    "AE95": 0.09329999999999997,
    "AE99": 0.09545999999999998,
    "fopt_mean": 0.4232,
    "fopt_sd": 0.028754902963572037
  },
  {
    "label": "table3_MaximumScore_d50",
    "name": "MaximumScore",
    "dim": 50,
    "maximize": true,
    "n_replications": 10,
    "best_opt": 0.482,
    "algo": "SMCO_R_EVO",
    "time_avg": 2.0126712578872685,
    "rMSE": 0.06075853849460172,
    "AE50": 0.069,
    "AE95": 0.07819999999999995,
    "AE99": 0.07963999999999996,
    "fopt_mean": 0.4266,
    "fopt_sd": 0.026298288917722387
  },
  {
    "label": "table3_MaximumScore_d50",
    "name": "MaximumScore",
    "dim": 50,
    "maximize": true,
    "n_replications": 10,
    "best_opt": 0.482,
    "algo": "SMCO_BR_EVO",
    "time_avg": 2.0999331811908633,
    "rMSE": 0.0674358954860095,
    "AE50": 0.063,
    "AE95": 0.09529999999999997,
    "AE99": 0.09745999999999998,
    "fopt_mean": 0.42060000000000003,
    "fopt_sd": 0.02939463291902867
  }
]